recursive_dictionary_update/__init__.py
recursive_dictionary_update-0.1.0.dist-info/DESCRIPTION.rst
recursive_dictionary_update-0.1.0.dist-info/METADATA
recursive_dictionary_update-0.1.0.dist-info/RECORD
recursive_dictionary_update-0.1.0.dist-info/WHEEL
recursive_dictionary_update-0.1.0.dist-info/metadata.json
recursive_dictionary_update-0.1.0.dist-info/top_level.txt
